jupyterlab_ou_brand_extension/.DS_Store
jupyterlab_ou_brand_extension/__init__.py
jupyterlab_ou_brand_extension/_version.py
jupyterlab_ou_brand_extension/labextension/package.json
jupyterlab_ou_brand_extension/labextension/static/561245dae1a5ab90b683.png
jupyterlab_ou_brand_extension/labextension/static/568.fdfdbda65961ca1d157d.js
jupyterlab_ou_brand_extension/labextension/static/747.50a84bac1d8c32847c0b.js
jupyterlab_ou_brand_extension/labextension/static/a74534f8c3ed21d3ac1b.png
jupyterlab_ou_brand_extension/labextension/static/remoteEntry.91537d272ddee019d9db.js
jupyterlab_ou_brand_extension/labextension/static/style.js
jupyterlab_ou_brand_extension/labextension/static/third-party-licenses.json
jupyterlab_ou_brand_extension-0.2.3.data/data/share/jupyter/labextensions/jupyterlab_ou_brand_extension/install.json
jupyterlab_ou_brand_extension-0.2.3.data/data/share/jupyter/labextensions/jupyterlab_ou_brand_extension/package.json
jupyterlab_ou_brand_extension-0.2.3.data/data/share/jupyter/labextensions/jupyterlab_ou_brand_extension/static/561245dae1a5ab90b683.png
jupyterlab_ou_brand_extension-0.2.3.data/data/share/jupyter/labextensions/jupyterlab_ou_brand_extension/static/568.fdfdbda65961ca1d157d.js
jupyterlab_ou_brand_extension-0.2.3.data/data/share/jupyter/labextensions/jupyterlab_ou_brand_extension/static/747.50a84bac1d8c32847c0b.js
jupyterlab_ou_brand_extension-0.2.3.data/data/share/jupyter/labextensions/jupyterlab_ou_brand_extension/static/a74534f8c3ed21d3ac1b.png
jupyterlab_ou_brand_extension-0.2.3.data/data/share/jupyter/labextensions/jupyterlab_ou_brand_extension/static/remoteEntry.91537d272ddee019d9db.js
jupyterlab_ou_brand_extension-0.2.3.data/data/share/jupyter/labextensions/jupyterlab_ou_brand_extension/static/style.js
jupyterlab_ou_brand_extension-0.2.3.data/data/share/jupyter/labextensions/jupyterlab_ou_brand_extension/static/third-party-licenses.json
jupyterlab_ou_brand_extension-0.2.3.dist-info/LICENSE
jupyterlab_ou_brand_extension-0.2.3.dist-info/METADATA
jupyterlab_ou_brand_extension-0.2.3.dist-info/WHEEL
jupyterlab_ou_brand_extension-0.2.3.dist-info/top_level.txt
jupyterlab_ou_brand_extension-0.2.3.dist-info/RECORD
